pylsp_isort/__init__.py
pylsp_isort/_version.py
pylsp_isort/plugin.py
python_lsp_isort-0.2.1.dist-info/METADATA
python_lsp_isort-0.2.1.dist-info/WHEEL
python_lsp_isort-0.2.1.dist-info/entry_points.txt
python_lsp_isort-0.2.1.dist-info/licenses/LICENSE
python_lsp_isort-0.2.1.dist-info/RECORD
