Metadata-Version: 2.4
Name: python-lsp-isort
Version: 0.2.1
Summary: isort plugin for the Python LSP Server
Project-URL: Homepage, https://github.com/chantera/python-lsp-isort
Project-URL: Bug Tracker, https://github.com/chantera/python-lsp-isort/issues
Author-email: Hiroki Teranishi <teranishi.hiroki@gmail.com>
License: MIT
License-File: LICENSE
Requires-Python: >=3.7
Requires-Dist: isort>=5.0
Requires-Dist: python-lsp-server
Provides-Extra: dev
Requires-Dist: mypy>=1.13; extra == 'dev'
Requires-Dist: pytest>=8.3; extra == 'dev'
Requires-Dist: ruff>=0.8; extra == 'dev'
Requires-Dist: tomli>=1.1.0; (python_version < '3.11') and extra == 'dev'
